joshbasiccalculator/__init__.py
alasry-0.0.1.dist-info/LICENCE.txt
alasry-0.0.1.dist-info/METADATA
alasry-0.0.1.dist-info/WHEEL
alasry-0.0.1.dist-info/top_level.txt
alasry-0.0.1.dist-info/RECORD
