Metadata-Version: 2.1
Name: alasry
Version: 0.0.1
Summary: alasry
Home-page: UNKNOWN
Author: alasry
Author-email: hashemshaiban@gmail.com
License: MIT
Keywords: alasry
Platform: UNKNOWN
Classifier: Development Status :: 5 - Production/Stable
Classifier: Intended Audience :: Education
Classifier: Operating System :: Microsoft :: Windows :: Windows 10
Classifier: License :: OSI Approved :: MIT License
Classifier: Programming Language :: Python :: 3
License-File: LICENCE.txt
